coca_ml/finance/indicator/__init__.py
coca_ml/finance/indicator/balance_of_power.py
coca_ml/finance/indicator/pivot_point.py
coca_ml/finance/indicator/utility.py
coca_ml/finance/indicator/vwap.py
coca_ml/finance/labeling/__init__.py
coca_ml/finance/labeling/get_bins_from_trend.py
coca_ml/finance/preprocessing/bar/__init__.py
coca_ml/finance/preprocessing/bar/cusum_bar.py
coca_ml/finance/preprocessing/bar/dollar_bar.py
coca_ml/finance/preprocessing/bar/vol_bar.py
coca_ml/finance/preprocessing/diff/__init__.py
coca_ml/finance/preprocessing/diff/difffunc.py
coca_ml/finance/preprocessing/diff/difffunc_ffd.py
coca_ml/finance/preprocessing/diff/fracdiff.py
coca_ml/finance/priceaction/__init__.py
coca_ml/finance/priceaction/barcrawler.py
coca_ml/finance/priceaction/reversal_hl.py
coca_ml/finance/priceaction/thrust_ud.py
coca_ml/timeseries/__init__.py
coca_ml/timeseries/models/__init__.py
coca_ml/timeseries/models/arlstm.py
coca_ml/timeseries/models/baseline.py
coca_ml/timeseries/window.py
coca_ml-0.0.16.dist-info/METADATA
coca_ml-0.0.16.dist-info/WHEEL
coca_ml-0.0.16.dist-info/RECORD
